LICENSE.txt
MANIFEST.in
README.rst
setup.py
auth_mac/__init__.py
auth_mac/admin.py
auth_mac/decorators.py
auth_mac/models.py
auth_mac/tools.py
auth_mac/utils.py
auth_mac/views.py
auth_mac/tests/__init__.py
auth_mac/tests/urls.py
auth_mac/tests/views.py
django_auth_mac.egg-info/PKG-INFO
django_auth_mac.egg-info/SOURCES.txt
django_auth_mac.egg-info/dependency_links.txt
django_auth_mac.egg-info/not-zip-safe
django_auth_mac.egg-info/requires.txt
django_auth_mac.egg-info/top_level.txt