Metadata-Version: 1.0
Name: django-auth-mac
Version: 0.1.2
Summary: Basic Django implementation of the draft RFC ietf-oauth-v2-http-mac-01
Home-page: https://github.com/ndevenish/auth_mac
Author: Nicholas Devenish
Author-email: n.devenish@gmail.com
License: Copyright (c) 2012 Nicholas Devenish <n.devenish@gmail.com>
